djaa_list_filter/__init__.py
djaa_list_filter/admin.py
djaa_list_filter/apps.py
djaa_list_filter/static/djaa_list_filter/admin/css/autocomplete_list_filter.css
djaa_list_filter/static/djaa_list_filter/admin/js/autocomplete_list_filter.js
djaa_list_filter/templates/djaa_list_filter/admin/filter/autocomplete_list_filter.html
django_admin_autocomplete_list_filter-1.0.0.dist-info/LICENCE
django_admin_autocomplete_list_filter-1.0.0.dist-info/METADATA
django_admin_autocomplete_list_filter-1.0.0.dist-info/WHEEL
django_admin_autocomplete_list_filter-1.0.0.dist-info/top_level.txt
django_admin_autocomplete_list_filter-1.0.0.dist-info/RECORD
