Metadata-Version: 2.1
Name: django-admin-autocomplete-list-filter
Version: 1.0.0
Summary: Ajax autocomplete list filter for Django admin
Home-page: https://github.com/demiroren-teknoloji/django-admin-autocomplete-list-filter
Author: Demirören Teknoloji Django Team
Author-email: account@demirorenteknoloji.com
License: MIT
Platform: UNKNOWN
Classifier: Development Status :: 4 - Beta
Classifier: Environment :: Web Environment
Classifier: Framework :: Django
Classifier: Framework :: Django :: 2.2
Classifier: Intended Audience :: Developers
Classifier: License :: OSI Approved :: MIT License
Classifier: Operating System :: OS Independent
Classifier: Programming Language :: Python :: 3
Classifier: Programming Language :: Python :: 3.7
Classifier: Programming Language :: Python :: 3 :: Only
Classifier: Topic :: Internet :: WWW/HTTP
Classifier: Topic :: Internet :: WWW/HTTP :: Dynamic Content
Requires-Python: >=3.0
License-File: LICENCE
